README.md
setup.py
openastro/__init__.py
openastro/exceptions.py
openastro/image.py
openastro.egg-info/PKG-INFO
openastro.egg-info/SOURCES.txt
openastro.egg-info/dependency_links.txt
openastro.egg-info/entry_points.txt
openastro.egg-info/requires.txt
openastro.egg-info/top_level.txt
openastro.egg-info/zip-safe