Metadata-Version: 1.1
Name: openastro
Version: 0.2
Summary: An python package (mostly a wrapper) for xtelescope.net, an open observatory project which started in Xinjiang, China.
Home-page: http://www.xtelescope.net
Author: Wen Gu
Author-email: emptyset110@gmail.com
License: Apache Software License
Keywords: astropy,openastro,astronomy
Platform: UNKNOWN
Classifier: License :: OSI Approved :: Apache Software License
Classifier: Programming Language :: Python
Classifier: Intended Audience :: Developers
Classifier: Operating System :: OS Independent
